yaloader/__init__.py
yaloader/base_config.py
yaloader/config_loader.py
yaloader/constructor.py
yaloader/dumper.py
yaloader/loader.py
yaloader/representer.py
yaloader/utils.py
yaloader-1.0.2.dist-info/LICENSE.txt
yaloader-1.0.2.dist-info/METADATA
yaloader-1.0.2.dist-info/WHEEL
yaloader-1.0.2.dist-info/top_level.txt
yaloader-1.0.2.dist-info/RECORD
